pynfold/Regularization.py
pynfold/__init__.py
pynfold/discretefunctions.py
pynfold/due.py
pynfold/foldFBU.py
pynfold/foldInvert.py
pynfold/foldIterative.py
pynfold/foldRegularised.py
pynfold/priors.py
pynfold/tikhonov.py
pynfold/version.py
pynfold/tests/__init__.py
pynfold/tests/test_RooUnfold.py
pynfold/tests/test_fbu_import.py
pynfold/tests/test_invert.py
pynfold/tests/test_iterative.py
pynfold/tests/test_tikonov.py
pynfold-0.1.dev0.dist-info/DESCRIPTION.rst
pynfold-0.1.dev0.dist-info/METADATA
pynfold-0.1.dev0.dist-info/RECORD
pynfold-0.1.dev0.dist-info/WHEEL
pynfold-0.1.dev0.dist-info/metadata.json
pynfold-0.1.dev0.dist-info/top_level.txt
