Metadata-Version: 2.0
Name: pynfold
Version: 0.1.dev0
Summary: pynFold: implementation of various solutions to unfoldngand the inverse problem 
Home-page: http://github.com/vincecr0ft/pynFold
Author: Vince Croft
Author-email: vincecroft@gmail.com
License: MIT
Platform: OS Independent
Classifier: Development Status :: 3 - Alpha
Classifier: Environment :: Console
Classifier: Intended Audience :: Science/Research
Classifier: License :: OSI Approved :: MIT License
Classifier: Operating System :: OS Independent
Classifier: Programming Language :: Python
Classifier: Topic :: Scientific/Engineering
Requires: numpy
Requires: matplotlib
Requires: pymc
Requires: scipy
Requires-Dist: numpy
Requires-Dist: matplotlib
Requires-Dist: pymc
Requires-Dist: scipy
